{
  "sorted_middleware": [],
  "middleware": {
    "/": {
      "files": [
        "server/edge/chunks/_14dba436._.js",
        "server/edge/chunks/[root-of-the-server]__7f489030._.js",
        "server/edge/chunks/edge-wrapper_0fb052c5.js"
      ],
      "name": "middleware",
      "page": "/",
      "matchers": [
        {
          "regexp": "/:nextData(_next/data/[^/]{1,})?/profile/:path*{(\\\\.json)}?",
          "originalSource": "/profile/:path*"
        },
        {
          "regexp": "/:nextData(_next/data/[^/]{1,})?/notes/:path*{(\\\\.json)}?",
          "originalSource": "/notes/:path*"
        },
        {
          "regexp": "/:nextData(_next/data/[^/]{1,})?/sign-in{(\\\\.json)}?",
          "originalSource": "/sign-in"
        },
        {
          "regexp": "/:nextData(_next/data/[^/]{1,})?/sign-up{(\\\\.json)}?",
          "originalSource": "/sign-up"
        }
      ],
      "wasm": [],
      "assets": [],
      "env": {
        "__NEXT_BUILD_ID": "development",
        "NEXT_SERVER_ACTIONS_ENCRYPTION_KEY": "/NJFyuei01o2UWYvecnZzGWv7ZFD9LbE3wVBZp9nqJo=",
        "__NEXT_PREVIEW_MODE_ID": "fb07c217b5a7d444fcee003d0e80cd4c",
        "__NEXT_PREVIEW_MODE_ENCRYPTION_KEY": "a872c3de0fbe37ea04b1484b6eca191c1ff128bd8b821360877ead7ef66ae747",
        "__NEXT_PREVIEW_MODE_SIGNING_KEY": "b568eb333eea41761eeffd759a2102eb2b6da816110f202ebf6b514a2649a83a"
      }
    }
  },
  "instrumentation": null,
  "functions": {}
}